setup.py
pdf2doi/__init__.py
pdf2doi/config.py
pdf2doi/find_title_via_pymupdf.py
pdf2doi/finders.py
pdf2doi/main.py
pdf2doi/patterns.py
pdf2doi4frappe_library-0.0.1.dist-info/METADATA
pdf2doi4frappe_library-0.0.1.dist-info/WHEEL
pdf2doi4frappe_library-0.0.1.dist-info/RECORD
