Metadata-Version: 2.1
Name: pdf2doi4frappe_library
Version: 0.0.1
Summary: extract the DOI or ISBN from a .pdf file
Project-URL: Homepage, https://github.com/abrefael/pdf2doi4frappe_library
Author-email: Alon Ben Refael <alon.ben.refael@gmail.com>
Classifier: License :: OSI Approved :: MIT License
Classifier: Operating System :: OS Independent
Classifier: Programming Language :: Python :: 3
Requires-Python: >=3.7
